CHANGELOG.txt
LICENCE.txt
MANIFEST.in
README.txt
setup.py
cyaxares/__init__.py
cyaxares.egg-info/PKG-INFO
cyaxares.egg-info/SOURCES.txt
cyaxares.egg-info/dependency_links.txt
cyaxares.egg-info/requires.txt
cyaxares.egg-info/top_level.txt