Metadata-Version: 2.1
Name: cyaxares
Version: 0.1
Summary: A dense medium radiative transfer equation solver using Monte Carlo method
Home-page: https://github.com/refetaliyalcin/cyaxares
Author: Refet Ali Yalcin
Author-email: refetali@gmail.com
License: MIT
Keywords: radiative transfer,monte carlo,colloids,Mie theory,Mie,Effective medium theory
Classifier: Development Status :: 5 - Production/Stable
Classifier: Operating System :: Unix
Classifier: Operating System :: MacOS :: MacOS X
Classifier: Operating System :: Microsoft :: Windows :: Windows 10
Classifier: License :: OSI Approved :: MIT License
Classifier: Programming Language :: Python :: 3
License-File: LICENCE.txt
